odoo8_addon_account_vat_on_payment-8.0.1.0.0.99.dev75-py3.8-nspkg.pth
odoo_addons/account_vat_on_payment/README.rst
odoo_addons/account_vat_on_payment/__init__.py
odoo_addons/account_vat_on_payment/__openerp__.py
odoo_addons/account_vat_on_payment/account_account.py
odoo_addons/account_vat_on_payment/account_account_view.xml
odoo_addons/account_vat_on_payment/account_bank_statement.py
odoo_addons/account_vat_on_payment/account_config_settings.py
odoo_addons/account_vat_on_payment/account_config_settings_view.xml
odoo_addons/account_vat_on_payment/account_demo.xml
odoo_addons/account_vat_on_payment/account_fiscal_position.py
odoo_addons/account_vat_on_payment/account_fiscal_position_view.xml
odoo_addons/account_vat_on_payment/account_invoice.py
odoo_addons/account_vat_on_payment/account_invoice_view.xml
odoo_addons/account_vat_on_payment/account_journal.py
odoo_addons/account_vat_on_payment/account_journal_view.xml
odoo_addons/account_vat_on_payment/account_move_line.py
odoo_addons/account_vat_on_payment/account_move_line_view.xml
odoo_addons/account_vat_on_payment/account_tax_code.py
odoo_addons/account_vat_on_payment/account_tax_code_view.xml
odoo_addons/account_vat_on_payment/account_voucher.py
odoo_addons/account_vat_on_payment/account_voucher_view.xml
odoo_addons/account_vat_on_payment/company.py
odoo_addons/account_vat_on_payment/i18n/account_vat_on_payment.pot
odoo_addons/account_vat_on_payment/i18n/am.po
odoo_addons/account_vat_on_payment/i18n/ar.po
odoo_addons/account_vat_on_payment/i18n/bg.po
odoo_addons/account_vat_on_payment/i18n/bs.po
odoo_addons/account_vat_on_payment/i18n/ca.po
odoo_addons/account_vat_on_payment/i18n/ca_ES.po
odoo_addons/account_vat_on_payment/i18n/cs.po
odoo_addons/account_vat_on_payment/i18n/da.po
odoo_addons/account_vat_on_payment/i18n/de.po
odoo_addons/account_vat_on_payment/i18n/el_GR.po
odoo_addons/account_vat_on_payment/i18n/en_GB.po
odoo_addons/account_vat_on_payment/i18n/es.po
odoo_addons/account_vat_on_payment/i18n/es_CR.po
odoo8_addon_account_vat_on_payment-8.0.1.0.0.99.dev75.dist-info/METADATA
odoo8_addon_account_vat_on_payment-8.0.1.0.0.99.dev75.dist-info/WHEEL
odoo8_addon_account_vat_on_payment-8.0.1.0.0.99.dev75.dist-info/namespace_packages.txt
odoo8_addon_account_vat_on_payment-8.0.1.0.0.99.dev75.dist-info/top_level.txt
odoo8_addon_account_vat_on_payment-8.0.1.0.0.99.dev75.dist-info/RECORD
